{
	"credit": "Made by AnminMakura",
	"parent": "cannon_wow",
	"texture_size": [32, 32],
	"textures": {
		"1": "3d_item/firework_star/entity/cannon_wow"
	},
	"elements": [
		{
			"from": [-5, 5, 5],
			"to": [1, 11, 11],
			"rotation": {"angle": -45, "axis": "x", "origin": [-2, 8, 8]},
			"faces": {
				"north": {"uv": [10, 1, 13, 4], "texture": "#1"},
				"east": {"uv": [10, 1, 13, 4], "texture": "#1"},
				"south": {"uv": [10, 1, 13, 4], "texture": "#1"},
				"west": {"uv": [10, 1, 13, 4], "rotation": 90, "texture": "#1"},
				"up": {"uv": [10, 1, 13, 4], "texture": "#1"},
				"down": {"uv": [9.5, 2, 12.5, 5], "texture": "#1"}
			}
		},
		{
			"from": [-4, 3, 3],
			"to": [0, 13, 13],
			"rotation": {"angle": -45, "axis": "x", "origin": [-2, 8, 8]},
			"faces": {
				"north": {"uv": [11, 3, 13, 8], "texture": "#1"},
				"east": {"uv": [11, 1, 16, 6], "texture": "#1"},
				"south": {"uv": [14, 0.5, 12, 5.5], "texture": "#1"},
				"west": {"uv": [8.5, 2.5, 13.5, 7.5], "texture": "#1"},
				"up": {"uv": [11.5, 5, 9.5, 0], "texture": "#1"},
				"down": {"uv": [11, 1.5, 13, 6.5], "texture": "#1"}
			}
		},
		{
			"from": [-2.999, -3.7, 4],
			"to": [-1.001, -0.7, 12],
			"rotation": {"angle": 0, "axis": "y", "origin": [-2, 0.3, 8]},
			"faces": {
				"north": {"uv": [11, 2.5, 11.999, 4], "texture": "#1"},
				"east": {"uv": [12, 6.5, 16, 8], "texture": "#1"},
				"south": {"uv": [14.5, 2, 15.499, 3.5], "texture": "#1"},
				"west": {"uv": [10, 5.5, 14, 7], "texture": "#1"},
				"up": {"uv": [0, 0, 0.999, 4], "texture": "#missing"},
				"down": {"uv": [10.5, 5.5, 11.499, 1.5], "texture": "#1"}
			}
		},
		{
			"from": [-3.5, -3.7, 5],
			"to": [-0.5, 8.3, 11],
			"rotation": {"angle": 0, "axis": "y", "origin": [-2, 0.3, 8]},
			"faces": {
				"north": {"uv": [10.5, 7, 9, 1], "texture": "#1"},
				"east": {"uv": [13, 2, 16, 8], "texture": "#1"},
				"south": {"uv": [10.5, 1.5, 12, 7.5], "texture": "#1"},
				"west": {"uv": [13, 2, 16, 8], "texture": "#1"},
				"up": {"uv": [11, 2.5, 12.5, 5.5], "texture": "#1"},
				"down": {"uv": [11.5, 0.5, 13, 3.5], "texture": "#1"}
			}
		},
		{
			"from": [-3, -3.24761, 5.81418],
			"to": [-1, 2.40925, 11.47103],
			"rotation": {"angle": 45, "axis": "x", "origin": [-2, 0.2161, 7.98232]},
			"faces": {
				"north": {"uv": [10.5, 0.5, 11.5, 3.32843], "texture": "#1"},
				"east": {"uv": [13.17157, 5, 16, 7.82843], "texture": "#1"},
				"south": {"uv": [11, 1.5, 12, 4.32843], "texture": "#1"},
				"west": {"uv": [9.67157, 5, 12.49999, 7.82843], "texture": "#1"},
				"up": {"uv": [14.5, 2, 15.5, 4.82843], "texture": "#1"},
				"down": {"uv": [13, 2.5, 14, 5.32843], "texture": "#1"}
			}
		},
		{
			"from": [-5, -5.7, 3],
			"to": [0, -3.7, 13],
			"rotation": {"angle": 0, "axis": "y", "origin": [-2, 0.3, 8]},
			"faces": {
				"north": {"uv": [10.5, 2.5, 13, 1.5], "texture": "#1"},
				"east": {"uv": [16, 3, 11, 4], "texture": "#1"},
				"south": {"uv": [11.5, 3.5, 9, 4.5], "texture": "#1"},
				"west": {"uv": [15.5, 6, 10.5, 7], "texture": "#1"},
				"up": {"uv": [12.5, 2, 10, 7], "texture": "#1"},
				"down": {"uv": [12.5, 2, 10, 7], "texture": "#1"}
			}
		},
		{
			"from": [-2.56066, -6.47487, 4],
			"to": [-0.02513, -3.93934, 12],
			"rotation": {"angle": -45, "axis": "z", "origin": [-2.5, -4, 7]},
			"faces": {
				"north": {"uv": [10.5, 2.5, 11.76777, 3.76777], "texture": "#1"},
				"east": {"uv": [8.5, 1, 12.5, 2.26777], "texture": "#1"},
				"south": {"uv": [13.5, 3, 14.76777, 4.26777], "texture": "#1"},
				"west": {"uv": [9, 5, 13, 6.26777], "texture": "#1"},
				"up": {"uv": [12, 2, 13.26777, 6], "texture": "#1"},
				"down": {"uv": [9.5, 5, 10.76777, 1], "texture": "#1"}
			}
		},
		{
			"from": [15, 5, 5],
			"to": [21, 11, 11],
			"rotation": {"angle": -45, "axis": "x", "origin": [18, 8, 8]},
			"faces": {
				"north": {"uv": [13, 1, 10, 4], "texture": "#1"},
				"east": {"uv": [10, 4, 13, 1], "rotation": 90, "texture": "#1"},
				"south": {"uv": [13, 1, 10, 4], "texture": "#1"},
				"west": {"uv": [13, 1, 10, 4], "texture": "#1"},
				"up": {"uv": [13, 1, 10, 4], "texture": "#1"},
				"down": {"uv": [12.5, 2, 9.5, 5], "texture": "#1"}
			}
		},
		{
			"from": [16, 3, 3],
			"to": [20, 13, 13],
			"rotation": {"angle": -45, "axis": "x", "origin": [18, 8, 8]},
			"faces": {
				"north": {"uv": [13, 3, 11, 8], "texture": "#1"},
				"east": {"uv": [13.5, 2.5, 8.5, 7.5], "texture": "#1"},
				"south": {"uv": [12, 0.5, 14, 5.5], "texture": "#1"},
				"west": {"uv": [16, 1, 11, 6], "texture": "#1"},
				"up": {"uv": [9.5, 5, 11.5, 0], "texture": "#1"},
				"down": {"uv": [13, 1.5, 11, 6.5], "texture": "#1"}
			}
		},
		{
			"from": [17.001, -3.7, 4],
			"to": [18.999, -0.7, 12],
			"rotation": {"angle": 0, "axis": "y", "origin": [18, 0.3, 8]},
			"faces": {
				"north": {"uv": [11.999, 2.5, 11, 4], "texture": "#1"},
				"east": {"uv": [14, 5.5, 10, 7], "texture": "#1"},
				"south": {"uv": [15.499, 2, 14.5, 3.5], "texture": "#1"},
				"west": {"uv": [16, 6.5, 12, 8], "texture": "#1"},
				"up": {"uv": [0.999, 0, 0, 4], "texture": "#missing"},
				"down": {"uv": [11.499, 5.5, 10.5, 1.5], "texture": "#1"}
			}
		},
		{
			"from": [16.5, -3.7, 5],
			"to": [19.5, 8.3, 11],
			"rotation": {"angle": 0, "axis": "y", "origin": [18, 0.3, 8]},
			"faces": {
				"north": {"uv": [9, 7, 10.5, 1], "texture": "#1"},
				"east": {"uv": [16, 2, 13, 8], "texture": "#1"},
				"south": {"uv": [12, 1.5, 10.5, 7.5], "texture": "#1"},
				"west": {"uv": [16, 2, 13, 8], "texture": "#1"},
				"up": {"uv": [12.5, 2.5, 11, 5.5], "texture": "#1"},
				"down": {"uv": [13, 0.5, 11.5, 3.5], "texture": "#1"}
			}
		},
		{
			"from": [17, -3.24761, 5.81418],
			"to": [19, 2.40925, 11.47103],
			"rotation": {"angle": 45, "axis": "x", "origin": [18, 0.2161, 7.98232]},
			"faces": {
				"north": {"uv": [11.5, 0.5, 10.5, 3.32843], "texture": "#1"},
				"east": {"uv": [12.49999, 5, 9.67157, 7.82843], "texture": "#1"},
				"south": {"uv": [12, 1.5, 11, 4.32843], "texture": "#1"},
				"west": {"uv": [16, 5, 13.17157, 7.82843], "texture": "#1"},
				"up": {"uv": [15.5, 2, 14.5, 4.82843], "texture": "#1"},
				"down": {"uv": [14, 2.5, 13, 5.32843], "texture": "#1"}
			}
		},
		{
			"from": [16, -5.7, 3],
			"to": [21, -3.7, 13],
			"rotation": {"angle": 0, "axis": "y", "origin": [18, 0.3, 8]},
			"faces": {
				"north": {"uv": [13, 2.5, 10.5, 1.5], "texture": "#1"},
				"east": {"uv": [10.5, 6, 15.5, 7], "texture": "#1"},
				"south": {"uv": [9, 3.5, 11.5, 4.5], "texture": "#1"},
				"west": {"uv": [11, 3, 16, 4], "texture": "#1"},
				"up": {"uv": [10, 2, 12.5, 7], "texture": "#1"},
				"down": {"uv": [10, 2, 12.5, 7], "texture": "#1"}
			}
		},
		{
			"from": [16.02513, -6.47487, 4],
			"to": [18.56066, -3.93934, 12],
			"rotation": {"angle": 45, "axis": "z", "origin": [18.5, -4, 7]},
			"faces": {
				"north": {"uv": [11.76777, 2.5, 10.5, 3.76777], "texture": "#1"},
				"east": {"uv": [13, 5, 9, 6.26777], "texture": "#1"},
				"south": {"uv": [14.76777, 3, 13.5, 4.26777], "texture": "#1"},
				"west": {"uv": [12.5, 1, 8.5, 2.26777], "texture": "#1"},
				"up": {"uv": [13.26777, 2, 12, 6], "texture": "#1"},
				"down": {"uv": [10.76777, 5, 9.5, 1], "texture": "#1"}
			}
		},
		{
			"from": [0, 0, 0],
			"to": [16, 16, 16],
			"rotation": {"angle": 0, "axis": "z", "origin": [8, 8, 0.75]},
			"faces": {
				"north": {"uv": [8, 0, 16, 8], "texture": "#1"},
				"east": {"uv": [16, 0, 8, 8], "texture": "#1"},
				"south": {"uv": [8, 0, 16, 8], "texture": "#1"},
				"west": {"uv": [8, 0, 16, 8], "texture": "#1"},
				"up": {"uv": [8, 0, 16, 8], "texture": "#1"},
				"down": {"uv": [8, 0, 16, 8], "texture": "#1"}
			}
		},
		{
			"from": [2, 2, -4],
			"to": [14, 14, -1],
			"rotation": {"angle": 0, "axis": "z", "origin": [8, 8, 0.75]},
			"faces": {
				"north": {"uv": [15, 1, 9, 7], "texture": "#1"},
				"east": {"uv": [14, 1, 15.5, 7], "texture": "#1"},
				"south": {"uv": [0, 16, 0, 16], "texture": "#1"},
				"west": {"uv": [8.5, 1, 10, 7], "texture": "#1"},
				"up": {"uv": [9, 0.5, 15, 2], "texture": "#1"},
				"down": {"uv": [9, 6, 15, 7.5], "texture": "#1"}
			}
		},
		{
			"from": [3, 3, 17],
			"to": [13, 13, 18],
			"rotation": {"angle": 0, "axis": "z", "origin": [8, 8, 0.75]},
			"faces": {
				"north": {"uv": [0, 16, 0, 16], "texture": "#1"},
				"east": {"uv": [14, 1.5, 14.5, 6.5], "texture": "#1"},
				"south": {"uv": [9.5, 1.5, 14.5, 6.5], "texture": "#1"},
				"west": {"uv": [9.5, 1.5, 10, 6.5], "texture": "#1"},
				"up": {"uv": [9.5, 1.5, 14.5, 2], "texture": "#1"},
				"down": {"uv": [9.5, 6, 14.5, 6.5], "texture": "#1"}
			}
		},
		{
			"from": [1, 1, -1],
			"to": [15, 15, 17],
			"rotation": {"angle": 0, "axis": "z", "origin": [8, 8, 0.75]},
			"faces": {
				"north": {"uv": [15.5, 0.5, 8.5, 7.5], "texture": "#1"},
				"east": {"uv": [12, 7.5, 12.5, 0.5], "texture": "#1"},
				"south": {"uv": [8.5, 0.5, 15.5, 7.5], "texture": "#1"},
				"west": {"uv": [10, 0.5, 10.5, 7.5], "texture": "#1"},
				"up": {"uv": [8.5, 2.5, 15.5, 2], "texture": "#1"},
				"down": {"uv": [15.5, 6, 8.5, 5.5], "texture": "#1"}
			}
		},
		{
			"from": [3, 3, -9],
			"to": [13, 13, -4],
			"rotation": {"angle": 0, "axis": "z", "origin": [8, 8, 0.75]},
			"faces": {
				"north": {"uv": [5, 0, 0, 5], "texture": "#1"},
				"east": {"uv": [13.5, 1.5, 16, 6.5], "texture": "#1"},
				"south": {"uv": [0, 0, 5, 5], "texture": "#missing"},
				"west": {"uv": [11, 1.5, 8.5, 6.5], "texture": "#1"},
				"up": {"uv": [10, 3, 15, 0.5], "texture": "#1"},
				"down": {"uv": [15, 5, 10, 7.5], "texture": "#1"}
			}
		}
	],
	"groups": [
		{
			"name": "group",
			"origin": [-2.5, -4, 7],
			"color": 0,
			"nbt": "{}",
			"children": [0, 1, 2, 3, 4, 5, 6]
		},
		{
			"name": "group",
			"origin": [-2.5, -4, 7],
			"color": 0,
			"nbt": "{}",
			"children": [7, 8, 9, 10, 11, 12, 13]
		},
		{
			"name": "group",
			"origin": [8, 8, 0.75],
			"color": 0,
			"nbt": "{}",
			"children": [14, 15, 16, 17, 18]
		}
	]
}